smoothlog/__init__.py
smoothlog/logger.py
smoothlog-0.1.3.dist-info/LICENSE
smoothlog-0.1.3.dist-info/METADATA
smoothlog-0.1.3.dist-info/WHEEL
smoothlog-0.1.3.dist-info/RECORD
