Metadata-Version: 2.1
Name: smoothlog
Version: 0.1.3
Summary: A nice and easy-to-use logger for python
Author: ColGroLoOl
Requires-Python: >=3.8
Classifier: Programming Language :: Python :: 3
Classifier: Programming Language :: Python :: 3.8
Classifier: Programming Language :: Python :: 3.9
Classifier: Programming Language :: Python :: 3.10
Classifier: Programming Language :: Python :: 3.11
